geno2phenotb/__init__.py
geno2phenotb/annotate_vcf.py
geno2phenotb/exec_mtbseq.sh
geno2phenotb/geno2phenotb.py
geno2phenotb/installation_test.py
geno2phenotb/parse_args.py
geno2phenotb/predict.py
geno2phenotb/preprocess.py
geno2phenotb/utils.py
geno2phenotb/vcf_columns_extractor.py
geno2phenotb/vcf_columns_extractor_geno.py
geno2phenotb/static/FZB_catalogue_2020-05-10_BRg_new_abbrevs_resistance_variants_only.tsv
geno2phenotb/static/AMK/AMK_RNCV_mcc_best_estimator.joblib
geno2phenotb/static/AMK/vcf_collection_low_freq_extended_targets_plus_ge100bp-upstream_lin_pheno_geno_AMK_coocc_columns_1_repeated.txt
geno2phenotb/static/CAP/CAP_RNCV_average_precision_best_estimator.joblib
geno2phenotb/static/CAP/CAP_RNCV_average_precision_best_estimator_feature_importances.npy
geno2phenotb/static/CAP/CAP_repeated_nested_cv_results.json
geno2phenotb/static/CAP/vcf_collection_low_freq_extended_targets_plus_ge100bp-upstream_lin_pheno_geno_CAP_coocc_columns_1_repeated.txt
geno2phenotb/static/DCS/DCS_RNCV_average_precision_best_estimator.joblib
geno2phenotb/static/DCS/DCS_RNCV_average_precision_best_estimator_feature_importances.npy
geno2phenotb/static/DCS/DCS_repeated_nested_cv_results.json
geno2phenotb/static/DCS/vcf_collection_low_freq_extended_targets_plus_ge100bp-upstream_lin_pheno_geno_DCS_coocc_columns_1_repeated.txt
geno2phenotb/static/EMB/EMB_RNCV_average_precision_best_estimator.joblib
geno2phenotb/static/EMB/EMB_RNCV_average_precision_best_estimator_feature_importances.npy
geno2phenotb/static/EMB/EMB_repeated_nested_cv_results.json
geno2phenotb/static/EMB/vcf_collection_low_freq_extended_targets_plus_ge100bp-upstream_lin_pheno_geno_EMB_coocc_columns_1_repeated.txt
geno2phenotb/static/ETH/ETH_RNCV_average_precision_best_estimator.joblib
geno2phenotb/static/ETH/ETH_RNCV_average_precision_best_estimator_feature_importances.npy
geno2phenotb/static/ETH/ETH_repeated_nested_cv_results.json
geno2phenoTB-1.0.1.dist-info/LICENSE.txt
geno2phenoTB-1.0.1.dist-info/METADATA
geno2phenoTB-1.0.1.dist-info/WHEEL
geno2phenoTB-1.0.1.dist-info/entry_points.txt
geno2phenoTB-1.0.1.dist-info/top_level.txt
geno2phenoTB-1.0.1.dist-info/RECORD
