Metadata-Version: 2.1
Name: geno2phenoTB
Version: 1.0.1
Summary: Machine learning based engine to predict Mycobacterium tuberculosis drug resistance using whole-genome sequencing data
Home-page: https://github.com/msmdev/geno2phenoTB
Author: Bernhard Reuter, Jules Kreuer
Author-email: bernhard-reuter@gmx.de
Maintainer: Bernhard Reuter
Maintainer-email: bernhard-reuter@gmx.de
License: LGPL-3.0-only
Project-URL: Documentation, https://geno2phenotb.readthedocs.io/en/latest/
Platform: Mac
Platform: Linux
Classifier: Development Status :: 5 - Production/Stable
Classifier: Programming Language :: Python
Requires-Python: ==3.8.17
License-File: LICENSE.txt
Requires-Dist: importlib-metadata
Provides-Extra: dev
Requires-Dist: setuptools ; extra == 'dev'
Requires-Dist: sphinx <7.0,>=5.0 ; extra == 'dev'
Requires-Dist: sphinx-autodoc-annotation ; extra == 'dev'
Requires-Dist: sphinx-autodoc-typehints >=1.10.3 ; extra == 'dev'
Requires-Dist: sphinx-copybutton ; extra == 'dev'
Requires-Dist: sphinx-last-updated-by-git ; extra == 'dev'
Requires-Dist: sphinx-rtd-theme ; extra == 'dev'
Requires-Dist: sphinxcontrib-spelling ==8.0 ; extra == 'dev'
Requires-Dist: mypy ==1.2 ; extra == 'dev'
Requires-Dist: pre-commit ; extra == 'dev'
